everytime/__init__.py
everytime/example.py
everytime-0.2.1.dist-info/LICENSE
everytime-0.2.1.dist-info/WHEEL
everytime-0.2.1.dist-info/METADATA
everytime-0.2.1.dist-info/RECORD
