Metadata-Version: 2.1
Name: everytime
Version: 0.2.1
Summary: Schedule asyncio coroutines
Home-page: https://github.com/meipp/every/
License: MIT
Author: meipp
Author-email: meipp@users.noreply.github.com
Requires-Python: >=3.10,<4.0
Classifier: License :: OSI Approved :: MIT License
Classifier: Programming Language :: Python :: 3
Classifier: Programming Language :: Python :: 3.10
Project-URL: Repository, https://github.com/meipp/every/
